spiro_network/__init__.py
spiro_network/loader.py
spiro_network/module/__init__.py
spiro_network/module/ipaddr.py
spiro_network/states/__init__.py
spiro_network/states/hostname.py
spiro_network-0.2.dist-info/LICENSE
spiro_network-0.2.dist-info/METADATA
spiro_network-0.2.dist-info/WHEEL
spiro_network-0.2.dist-info/entry_points.txt
spiro_network-0.2.dist-info/top_level.txt
spiro_network-0.2.dist-info/RECORD
