Metadata-Version: 2.1
Name: spiro-network
Version: 0.2
Summary: Salt modules for discovering and exposing minion's IP addresses
Home-page: https://gitlab.com/spirostack/spiro-network
Author: Jamie Bliss
Author-email: jamie@ivyleav.es
License: UNKNOWN
Project-URL: Bug Reports, https://gitlab.com/spirostack/spiro-network/issues
Project-URL: Tip Jar, https://ko-fi.com/astraluma
Project-URL: Source, https://gitlab.com/spirostack/spiro-network/
Keywords: salt saltstack spirostack salt-extension
Platform: UNKNOWN
Classifier: Development Status :: 4 - Beta
Classifier: Intended Audience :: Developers
Classifier: Intended Audience :: System Administrators
Classifier: Environment :: Other Environment
Classifier: Operating System :: OS Independent
Classifier: Topic :: System :: Systems Administration
Classifier: License :: OSI Approved :: GNU Affero General Public License v3
Classifier: Programming Language :: Python :: 3
Classifier: Programming Language :: Python :: 3.5
Classifier: Programming Language :: Python :: 3.6
Classifier: Programming Language :: Python :: 3.7
Classifier: Programming Language :: Python :: 3.8
Classifier: Programming Language :: Python :: 3.9
Requires-Dist: requests
Requires-Dist: setuptools
